miyadaiku/themes/fullpagejs/__init__.py
miyadaiku/themes/fullpagejs/config.yml
miyadaiku/themes/fullpagejs/files/static/fullpage_js/fullpage.css
miyadaiku/themes/fullpagejs/files/static/fullpage_js/fullpage.extensions.min.js
miyadaiku/themes/fullpagejs/files/static/fullpage_js/fullpage.js
miyadaiku/themes/fullpagejs/files/static/fullpage_js/fullpage.min.css
miyadaiku/themes/fullpagejs/files/static/fullpage_js/fullpage.min.js
miyadaiku/themes/fullpagejs/files/static/fullpage_js/jquery.fullpage.min.css
miyadaiku/themes/fullpagejs/files/static/fullpage_js/jquery.fullpage.min.js
miyadaiku/themes/fullpagejs/templates/macros.html
miyadaiku.themes.fullpagejs-0.0.2.dist-info/DESCRIPTION.rst
miyadaiku.themes.fullpagejs-0.0.2.dist-info/METADATA
miyadaiku.themes.fullpagejs-0.0.2.dist-info/RECORD
miyadaiku.themes.fullpagejs-0.0.2.dist-info/WHEEL
miyadaiku.themes.fullpagejs-0.0.2.dist-info/metadata.json
miyadaiku.themes.fullpagejs-0.0.2.dist-info/top_level.txt
