Metadata-Version: 2.0
Name: miyadaiku.themes.fullpagejs
Version: 0.0.2
Summary: fullPage.js files for miyadaiku static site generator
Home-page: UNKNOWN
Author: Atsuo Ishimoto
Author-email: UNKNOWN
License: MIT
Platform: UNKNOWN
Classifier: Programming Language :: Python :: 3
Classifier: Programming Language :: Python :: 3.6
Requires-Dist: miyadaiku
Requires-Dist: miyadaiku.themes.jquery
